bs4/__init__.py
bs4/_deprecation.py
bs4/_typing.py
bs4/_warnings.py
bs4/css.py
bs4/dammit.py
bs4/diagnose.py
bs4/element.py
bs4/exceptions.py
bs4/filter.py
bs4/formatter.py
bs4/py.typed
bs4/builder/__init__.py
bs4/builder/_html5lib.py
bs4/builder/_htmlparser.py
bs4/builder/_lxml.py
beautifulsoup4-4.14.1.dist-info/METADATA
beautifulsoup4-4.14.1.dist-info/WHEEL
beautifulsoup4-4.14.1.dist-info/licenses/AUTHORS
beautifulsoup4-4.14.1.dist-info/licenses/LICENSE
beautifulsoup4-4.14.1.dist-info/RECORD
